nmeautils/__init__.py
nmeautils-1.0.dist-info/DESCRIPTION.rst
nmeautils-1.0.dist-info/METADATA
nmeautils-1.0.dist-info/RECORD
nmeautils-1.0.dist-info/WHEEL
nmeautils-1.0.dist-info/metadata.json
nmeautils-1.0.dist-info/top_level.txt
