Metadata-Version: 1.1
Name: nmeautils
Version: 1.0
Summary: read/parse NMEA with Python
Home-page: https://github.com/scivision/nmeautils
Author: Michael Hirsch, Ph.D.
Author-email: UNKNOWN
License: UNKNOWN
Platform: UNKNOWN
Classifier: Intended Audience :: Science/Research
Classifier: Development Status :: 5 - Production/Stable
Classifier: License :: OSI Approved :: MIT License
Classifier: Topic :: Scientific/Engineering
Classifier: Programming Language :: Python :: 3
